coroutincache/__init__.py
coroutincache/coroutincache.py
coroutincache/exceptions.py
coroutincache-1.5.0.dist-info/LICENSE
coroutincache-1.5.0.dist-info/METADATA
coroutincache-1.5.0.dist-info/WHEEL
coroutincache-1.5.0.dist-info/RECORD
